basecampx
