Metadata-Version: 1.1
Name: basecampx
Version: 0.1.5
Summary: Wrapper for Basecamp Next API.
Home-page: https://github.com/nous-consulting/basecamp-next
Author: Rimvydas Naktinis
Author-email: naktinis@gmail.com
License: MIT
Keywords: basecamp bcx api
Platform: UNKNOWN
Classifier: Development Status :: 3 - Alpha
Classifier: Intended Audience :: Developers
Classifier: License :: OSI Approved :: MIT License
Classifier: Natural Language :: English
Classifier: Operating System :: OS Independent
Classifier: Programming Language :: Python :: 2.7
